gameta/__init__.py
gameta/apply.py
gameta/cli.py
gameta/cmd.py
gameta/constants.py
gameta/context.py
gameta/init.py
gameta/params.py
gameta/repos.py
gameta/tags.py
gameta-0.2.7.dist-info/entry_points.txt
gameta-0.2.7.dist-info/LICENSE
gameta-0.2.7.dist-info/WHEEL
gameta-0.2.7.dist-info/METADATA
gameta-0.2.7.dist-info/RECORD
