Metadata-Version: 2.1
Name: gameta
Version: 0.2.7
Summary: CLI Tool for managing meta-repositories
Home-page: https://genius-systems.github.io/gameta
License: MIT
Keywords: metarepositories,repositories,shell,git
Author: David Lee
Author-email: ltw_david@hotmail.com
Requires-Python: >=3.6
Classifier: Development Status :: 4 - Beta
Classifier: Intended Audience :: Developers
Classifier: License :: OSI Approved :: MIT License
Classifier: Operating System :: POSIX :: Linux
Classifier: Programming Language :: Python :: 3
Classifier: Programming Language :: Python :: 3.6
Classifier: Programming Language :: Python :: 3.7
Classifier: Programming Language :: Python :: 3.8
Classifier: Programming Language :: Python :: 3.9
Classifier: Topic :: Software Development :: Build Tools
Classifier: Topic :: Terminals
Requires-Dist: Click (>=7.1.2,<8.0.0)
Requires-Dist: colorama (>=0.4.3,<0.5.0)
Requires-Dist: gitpython (>=3.1.9,<4.0.0)
Requires-Dist: jsonschema (>=3.2.0,<4.0.0)
Project-URL: Documentation, https://genius-systems.github.io/gameta
Project-URL: Repository, https://github.com/genius-systems/gameta
